time_monitor/__init__.py
time_monitor/activity.py
time_monitor/config.py
time_monitor/invoice.py
time_monitor/report.py
time_monitoring-0.0.1.data/data/latex/invoice/constants.tex
time_monitoring-0.0.1.data/data/latex/invoice/main.tex
time_monitoring-0.0.1.data/data/latex/invoice/preambule.tex
time_monitoring-0.0.1.data/scripts/activity
time_monitoring-0.0.1.data/scripts/begin
time_monitoring-0.0.1.data/scripts/invoice
time_monitoring-0.0.1.data/scripts/message
time_monitoring-0.0.1.data/scripts/report
time_monitoring-0.0.1.data/scripts/setup_time_report
time_monitoring-0.0.1.data/scripts/stats
time_monitoring-0.0.1.data/scripts/stop
time_monitoring-0.0.1.dist-info/LICENSE.txt
time_monitoring-0.0.1.dist-info/METADATA
time_monitoring-0.0.1.dist-info/WHEEL
time_monitoring-0.0.1.dist-info/top_level.txt
time_monitoring-0.0.1.dist-info/RECORD
