Metadata-Version: 2.1
Name: time-monitoring
Version: 0.0.1
Summary: Time monitoring with shell commands,
Home-page: https://github.com/VivienCabannes/time-monitoring
Author: Vivien Cabannes
Author-email: vivien.cabannes@gmail.com,
License: UNKNOWN
Project-URL: Bug Tracker, https://github.com/VivienCabannes/time-monitoring/issues
Platform: UNKNOWN
Classifier: Programming Language :: Python :: 3
Classifier: License :: OSI Approved :: MIT License
Classifier: Operating System :: OS Independent
Requires-Python: >=3.6
License-File: LICENSE.txt
